odoo/addons/l10n_ee_accounting/README.rst
odoo/addons/l10n_ee_accounting/__init__.py
odoo/addons/l10n_ee_accounting/__manifest__.py
odoo/addons/l10n_ee_accounting/data/account.account.template.csv
odoo/addons/l10n_ee_accounting/data/account_chart_template.xml
odoo/addons/l10n_ee_accounting/data/account_chart_template_configure.xml
odoo/addons/l10n_ee_accounting/data/account_fiscal_position_template.xml
odoo/addons/l10n_ee_accounting/data/account_group_template.xml
odoo/addons/l10n_ee_accounting/data/account_tax_group.xml
odoo/addons/l10n_ee_accounting/data/account_tax_template.xml
odoo/addons/l10n_ee_accounting/data/balance_sheet.xml
odoo/addons/l10n_ee_accounting/data/income_statement.xml
odoo/addons/l10n_ee_accounting/data/kmd_2017.xml
odoo/addons/l10n_ee_accounting/i18n/l10n_ee_accounting.pot
odoo/addons/l10n_ee_accounting/readme/CONTRIBUTORS.rst
odoo/addons/l10n_ee_accounting/readme/CREDITS.rst
odoo/addons/l10n_ee_accounting/readme/DESCRIPTION.rst
odoo/addons/l10n_ee_accounting/static/description/icon.png
odoo/addons/l10n_ee_accounting/static/description/index.html
odoo_addon_l10n_ee_accounting-15.0.1.2.1.2.dist-info/METADATA
odoo_addon_l10n_ee_accounting-15.0.1.2.1.2.dist-info/WHEEL
odoo_addon_l10n_ee_accounting-15.0.1.2.1.2.dist-info/top_level.txt
odoo_addon_l10n_ee_accounting-15.0.1.2.1.2.dist-info/RECORD
